{
  "9097": {
    "id": "9097",
    "inexperienced": [],
    "alternatives": [],
    "participants": [
      {
        "username": "Papu",
        "id": "489214493503520778"
      },
      {
        "username": "Ionut Dinu",
        "id": "410110931578912781"
      }
    ],
    "dueDate": 1635271200000,
    "desc": "3 cp",
    "creator": {
      "username": "Papu",
      "id": "489214493503520778"
    },
    "activity": "Vault Of Glass",
    "messageID": "901862108952682568"
  },
  "0407": {
    "id": "0407",
    "inexperienced": [],
    "alternatives": [],
    "participants": [
      {
        "username": "The__charmer",
        "id": "266305540307681280"
      },
      {
        "username": "gogu",
        "id": "726537242323058710"
      },
      {
        "username": "DerionX(Raul)",
        "id": "303603232012369931"
      },
      {
        "username": "Flavius l Muramassa",
        "id": "154260288374308865"
      },
      {
        "username": "Perl",
        "id": "107872166720077824"
      },
      {
        "username": "OREZ CU LAPTE",
        "id": "438034897425399808"
      }
    ],
    "dueDate": 1635267600000,
    "desc": "Fara incepatori",
    "creator": {
      "username": "The__charmer",
      "id": "266305540307681280"
    },
    "activity": "Vault Of Glass",
    "messageID": "901790459658108990"
  }
}