{
  "5022": {
    "id": "5022",
    "inexperienced": [],
    "alternatives": [
      {
        "username": "Haures",
        "id": "391337571139190786"
      }
    ],
    "participants": [
      {
        "username": "Testyment",
        "id": "492731788079267840"
      },
      {
        "username": "EvilPrime",
        "id": "244442588638085121"
      },
      {
        "username": "Ra's Al Ghul (K3ntXD)",
        "id": "614544813530021920"
      },
      {
        "username": "Emyl",
        "id": "212966366729207808"
      }
    ],
    "dueDate": 1622998800000,
    "desc": "doar boss \nfacem de 2 ori daca se poate:)",
    "creator": {
      "username": "Testyment",
      "id": "492731788079267840"
    },
    "activity": "Vault Of Glass",
    "messageID": "850839099685994517"
  }
}