{
  "1070": {
    "id": "1070",
    "inexperienced": [
      {
        "id": "671655253296283660",
        "username": "GeorgeeE"
      },
      {
        "id": "266305540307681280",
        "username": "ConceptioNNN"
      }
    ],
    "alternatives": [],
    "participants": [
      {
        "username": "ConceptioNNN",
        "id": "266305540307681280"
      },
      {
        "username": "GeorgeeE",
        "id": "671655253296283660"
      },
      {
        "username": "Wu Wei",
        "id": "291565012361805824"
      }
    ],
    "dueDate": 1627808400000,
    "desc": "Pentru divinity, 2 incepatori maxim",
    "creator": {
      "username": "ConceptioNNN",
      "id": "266305540307681280"
    },
    "activity": "Garden of Salvation",
    "messageID": "871145548542009414"
  }
}